s3_utility.py
mys3Utility1-0.0.2.dist-info/METADATA
mys3Utility1-0.0.2.dist-info/WHEEL
mys3Utility1-0.0.2.dist-info/top_level.txt
mys3Utility1-0.0.2.dist-info/RECORD
