Metadata-Version: 2.1
Name: mys3Utility1
Version: 0.0.2
Summary: s3 utility lib
Home-page: UNKNOWN
Author: mohit
Author-email: foomail@foo.com
License: UNKNOWN
Platform: UNKNOWN
Requires-Dist: boto3 (>=1.2)
